pyHugo/__init__.py
pyHugo/__main__.py
pyHugo/configs.py
pyHugo/version.py
pyHugo/dB/__init__.py
pyHugo/dB/_core.py
pyHugo/dB/afk_db.py
pyHugo/dB/antiflood_db.py
pyHugo/dB/asst_fns.py
pyHugo/dB/asstcmd_db.py
pyHugo/dB/blacklist_chat_db.py
pyHugo/dB/blacklist_db.py
pyHugo/dB/botchat_db.py
pyHugo/dB/broadcast_db.py
pyHugo/dB/ch_db.py
pyHugo/dB/chatBot_db.py
pyHugo/dB/clean_db.py
pyHugo/dB/echo_db.py
pyHugo/dB/filter_db.py
pyHugo/dB/forcesub_db.py
pyHugo/dB/gban_mute_db.py
pyHugo/dB/gcast_blacklist_db.py
pyHugo/dB/greetings_db.py
pyHugo/dB/logusers_db.py
pyHugo/dB/mute_db.py
pyHugo/dB/night_db.py
pyHugo/dB/notes_db.py
pyHugo/dB/nsfw_db.py
pyHugo/dB/pmpermit_db.py
pyHugo/dB/snips_db.py
pyHugo/dB/sudos.py
pyHugo/dB/username_db.py
pyHugo/dB/vc_group.py
pyHugo/dB/vc_sudos.py
pyHugo/dB/warn_db.py
pyHugo/functions/FastTelethon.py
pyHugo/functions/__init__.py
pyHugo/functions/admins.py
pyHugo/functions/gdrive.py
pyHugo/functions/google_image.py
pyHugo/functions/helper.py
pyHugo/functions/info.py
pyHugo/functions/misc.py
pyHugo/functions/tools.py
pyHugo/functions/ytdl.py
pyHugo/misc/__init__.py
pyHugo/misc/_assistant.py
pyHugo/misc/_decorators.py
pyHugo/misc/_supporter.py
pyHugo/misc/_wrappers.py
pyHugo/startup/BaseClient.py
pyHugo/startup/__init__.py
pyHugo/startup/connections.py
pyHugo/startup/exceptions.py
pyHugo/startup/funcs.py
pyHugo/startup/loader.py
pyHugo/startup/utils.py
py_Hugo-0.1.1.dist-info/LICENSE
py_Hugo-0.1.1.dist-info/METADATA
py_Hugo-0.1.1.dist-info/WHEEL
py_Hugo-0.1.1.dist-info/top_level.txt
py_Hugo-0.1.1.dist-info/RECORD
