Metadata-Version: 2.1
Name: py-Hugo
Version: 0.1.1
Summary: A Secure and Powerful Python-Telethon Based Library For Hugo Userbot.
Home-page: https://github.com/TeamHugoX/pyHugo
Author: TeamHugo
Author-email: saycosanz@gmail.com
License: GNU AFFERO GENERAL PUBLIC LICENSE (v3)
Project-URL: Bug Tracker, https://github.com/TeamHugoX/py-Hugo/issues
Project-URL: Source Code, https://github.com/TeamHugoX/pyHugo
Platform: UNKNOWN
Classifier: Programming Language :: Python :: 3
Classifier: Programming Language :: Python :: 3.6
Classifier: Programming Language :: Python :: 3.7
Classifier: Programming Language :: Python :: 3.8
Classifier: Programming Language :: Python :: 3.9
Classifier: License :: OSI Approved :: GNU General Public License v3 (GPLv3)
Classifier: Operating System :: OS Independent
Requires-Python: >=3.6
License-File: LICENSE
Requires-Dist: redis
Requires-Dist: python-decouple (==3.3)
Requires-Dist: python-dotenv (==0.15.0)
Requires-Dist: aiofiles
Requires-Dist: aiohttp[speedups]
Requires-Dist: hiredis
Requires-Dist: psycopg2-binary
